{"GlobalPropertiesHash":"Pgl3rv96f7dNzLmMskxJWK43ZX/z+DB/2cawXQUmwrU=","FingerprintPatternsHash":"gq3WsqcKBUGTSNle7RKKyXRIwh7M8ccEqOqYvIzoM04=","PropertyOverridesHash":"8ZRc1sGeVrPBx4lD717BgRaQekyh78QKV9SKsdt638U=","InputHashes":["adS/uiHr\u002BKPQRamLw8ax\u002BFX4PqdEuBMiha9vHvk2ztw=","RU9VwOWO/YVnEZ777ZK0H4fHAnorvadxbBkZcJTDSZs=","5Bt3JKNUMa7Qv09XOsUdZp/02je\u002BP3iOfe4sPE0YbEM=","xpkJgrpMfy2d4Y\u002BBtNn6aJgRADB/cBC44QdD5ZUUL3w=","n4BP7UwxrlnXc5faVpMlimg7CY5VeaBA3fWcqY7Y3pE=","0vmHGhEcjxJxE9UlRsSZF616waujaFuey0JZ0qq1tGM=","fHJ9WDOx015/b\u002Bq45CCq4A\u002BDaGkI0wodDKPWBYzssaw=","QXjRQhLg2Js8\u002Bj4xFpHQo7XbEMkd4FhxQj8MHgK4a0o=","CYsh96Ktq3NJuuwfp5CaRUCGc8\u002BGb2zfXn6psaM973E=","nPLJNDah1Z0cRIsnCnIjWs/YLb1emGZ4O0bx5mlPaLc=","LyvSsSkVIbZ3292LaPuwZVWcmvJcZOa9azBZeQYG7Iw=","FrV8jdkJqSDvw3ore3jW3uD/KYtsnqS9NOoKv66meCQ=","GJ7cftWF3rDzSYtsNtVTkHa9q3imFJ2niPTYisgU3S8=","Iu2BpEsQAnkiwMzCAMxdcp/ze1KIZjwQ6nDE69mpXhI=","SJ5ZDBZgCm8cuy1m/oWwVgLTQBZjWK5uIKi8yontl84=","h3XMfdqblLF4yYeHjfFIQghFFSxR0IYygRZZEUxnVCI=","c8KxDuCX9H5E1bNQLT7sdUXdSo9UHrUBUPbyrDQyRok=","mshqV7RNKI/zjkrqKfz4rFk6XyGRGZgjfZVjA0j2okQ=","JWZpCwETsApNW1hcp9mxdCkB8MzOazRuCu330h6RBn8=","njyi1Wwg/A2K8CoLhMtFfmQYAvX4gy68sR\u002Br0bAxWzw=","PTz6\u002B/pNrwuTQR2t23JEg1aMfBGLg2YtSrXGoah8a6g=","uAvNU5AJO9OwYJ42VkdYyvNo9ST4W/fa\u002B1RPgxztXGQ=","Gs4ZpsE5ukXYrbpVg/gMXxxOWwPJPFnxNPQPay2r0Mc=","qhJApNgzSk\u002BUxx6M8ksgqCXr0566pJNlv/UVjXBpUus=","g6fXc6qMcpNkrpzuXsDXplZsaLRaWs\u002BysVOGIeDD\u002BuY=","PAOtwT\u002BVmzWbeleg2IzES2lFUCvaWb6AeMtOZeXavjU=","qIcVGL8QUA1Yic9BPPKYaqQwaJ89oXZo8WAOw8E6AGs=","N3r\u002BdL5XSPA8AvKBQvD8vVWRsuBRt669r6\u002Ba/svrHys=","NYtcuqvjYk3mg9w5e7k8ELz8njkQokbBAJjDWUJuI40=","4ZMWFWm0ynvuOwtLVe7MGK7ySanpo2xd7HDBECRpTkQ=","zLTG5jugf0NHqV0CQe6i1b\u002BRH7cUXS5w63vUlt9IS30=","kfVexCzatEDLx3qUadJ8AGldScgUqw55gIF\u002BUYYP4wk=","NmZzeyOaj2EGpibJxccARJV6xWGG9H\u002BC7lQNbXFr0l0=","swkDuv1gx4Sk8ETDBaj6cC9ZU5Egow3i6qiu6LgITNM="],"CachedAssets":{"adS/uiHr\u002BKPQRamLw8ax\u002BFX4PqdEuBMiha9vHvk2ztw=":{"Identity":"C:\\aaaaaa\\GestionCalidad\\wwwroot\\css\\styles.css","SourceId":"GestionCalidad","SourceType":"Discovered","ContentRoot":"C:\\aaaaaa\\GestionCalidad\\wwwroot\\","BasePath":"/","RelativePath":"css/styles#[.{fingerprint}]?.css","AssetKind":"All","AssetMode":"All","AssetRole":"Primary","AssetMergeBehavior":null,"AssetMergeSource":"","RelatedAsset":null,"AssetTraitName":null,"AssetTraitValue":null,"Fingerprint":"kgdubres10","Integrity":"XEkezFFKs06mp4/iCWkI3btGrRwsKgjQRes4mcSVGbc=","CopyToOutputDirectory":"Never","CopyToPublishDirectory":"PreserveNewest","OriginalItemSpec":"wwwroot\\css\\styles.css","FileLength":1537,"LastWriteTime":"2026-05-06T06:00:25.10666+00:00"},"xpkJgrpMfy2d4Y\u002BBtNn6aJgRADB/cBC44QdD5ZUUL3w=":{"Identity":"C:\\aaaaaa\\GestionCalidad\\wwwroot\\js\\enfermeras.js","SourceId":"GestionCalidad","SourceType":"Discovered","ContentRoot":"C:\\aaaaaa\\GestionCalidad\\wwwroot\\","BasePath":"/","RelativePath":"js/enfermeras#[.{fingerprint}]?.js","AssetKind":"All","AssetMode":"All","AssetRole":"Primary","AssetMergeBehavior":null,"AssetMergeSource":"","RelatedAsset":null,"AssetTraitName":null,"AssetTraitValue":null,"Fingerprint":"x89vtlpnmp","Integrity":"kUEXN9oFp9JIn4lpz401VI19kB0QsGuA9dmsSdacwQI=","CopyToOutputDirectory":"Never","CopyToPublishDirectory":"PreserveNewest","OriginalItemSpec":"wwwroot\\js\\enfermeras.js","FileLength":723,"LastWriteTime":"2026-05-06T06:59:39.4928941+00:00"},"RU9VwOWO/YVnEZ777ZK0H4fHAnorvadxbBkZcJTDSZs=":{"Identity":"C:\\aaaaaa\\GestionCalidad\\wwwroot\\index.html","SourceId":"GestionCalidad","SourceType":"Discovered","ContentRoot":"C:\\aaaaaa\\GestionCalidad\\wwwroot\\","BasePath":"/","RelativePath":"index#[.{fingerprint}]?.html","AssetKind":"All","AssetMode":"All","AssetRole":"Primary","AssetMergeBehavior":null,"AssetMergeSource":"","RelatedAsset":null,"AssetTraitName":null,"AssetTraitValue":null,"Fingerprint":"6f3w81hrez","Integrity":"rqoGCvpDh96VFx9kv0ybQxwpuN8fTIG1iOIq/NJO2oc=","CopyToOutputDirectory":"Never","CopyToPublishDirectory":"PreserveNewest","OriginalItemSpec":"wwwroot\\index.html","FileLength":1383,"LastWriteTime":"2026-05-06T12:27:19.7080116+00:00"},"0vmHGhEcjxJxE9UlRsSZF616waujaFuey0JZ0qq1tGM=":{"Identity":"C:\\aaaaaa\\GestionCalidad\\wwwroot\\js\\informeQuejaDepartamento.js","SourceId":"GestionCalidad","SourceType":"Discovered","ContentRoot":"C:\\aaaaaa\\GestionCalidad\\wwwroot\\","BasePath":"/","RelativePath":"js/informeQuejaDepartamento#[.{fingerprint}]?.js","AssetKind":"All","AssetMode":"All","AssetRole":"Primary","AssetMergeBehavior":null,"AssetMergeSource":"","RelatedAsset":null,"AssetTraitName":null,"AssetTraitValue":null,"Fingerprint":"n6kt478won","Integrity":"kXQFQBNwoeq7UUxWgXTGUvpud0\u002BimsI99u3RmsZH0FU=","CopyToOutputDirectory":"Never","CopyToPublishDirectory":"PreserveNewest","OriginalItemSpec":"wwwroot\\js\\informeQuejaDepartamento.js","FileLength":2353,"LastWriteTime":"2026-05-06T12:14:21.612723+00:00"},"QXjRQhLg2Js8\u002Bj4xFpHQo7XbEMkd4FhxQj8MHgK4a0o=":{"Identity":"C:\\aaaaaa\\GestionCalidad\\wwwroot\\js\\quejas.js","SourceId":"GestionCalidad","SourceType":"Discovered","ContentRoot":"C:\\aaaaaa\\GestionCalidad\\wwwroot\\","BasePath":"/","RelativePath":"js/quejas#[.{fingerprint}]?.js","AssetKind":"All","AssetMode":"All","AssetRole":"Primary","AssetMergeBehavior":null,"AssetMergeSource":"","RelatedAsset":null,"AssetTraitName":null,"AssetTraitValue":null,"Fingerprint":"97h2vy57zk","Integrity":"lRpIa/chJLx11kLZDWxBHn9nxrg14vGL5c2IpeqkNu8=","CopyToOutputDirectory":"Never","CopyToPublishDirectory":"PreserveNewest","OriginalItemSpec":"wwwroot\\js\\quejas.js","FileLength":1544,"LastWriteTime":"2026-05-06T12:21:46.2993478+00:00"},"5Bt3JKNUMa7Qv09XOsUdZp/02je\u002BP3iOfe4sPE0YbEM=":{"Identity":"C:\\aaaaaa\\GestionCalidad\\wwwroot\\js\\departamentos.js","SourceId":"GestionCalidad","SourceType":"Discovered","ContentRoot":"C:\\aaaaaa\\GestionCalidad\\wwwroot\\","BasePath":"/","RelativePath":"js/departamentos#[.{fingerprint}]?.js","AssetKind":"All","AssetMode":"All","AssetRole":"Primary","AssetMergeBehavior":null,"AssetMergeSource":"","RelatedAsset":null,"AssetTraitName":null,"AssetTraitValue":null,"Fingerprint":"ah2o1dinpu","Integrity":"jvd8TZS1w/5za/B2qO7w5v7CcH4qMO0qi7awpwbCSbo=","CopyToOutputDirectory":"Never","CopyToPublishDirectory":"PreserveNewest","OriginalItemSpec":"wwwroot\\js\\departamentos.js","FileLength":1168,"LastWriteTime":"2026-05-06T05:37:52.1535938+00:00"},"nPLJNDah1Z0cRIsnCnIjWs/YLb1emGZ4O0bx5mlPaLc=":{"Identity":"C:\\aaaaaa\\GestionCalidad\\wwwroot\\pages\\departamentos.html","SourceId":"GestionCalidad","SourceType":"Discovered","ContentRoot":"C:\\aaaaaa\\GestionCalidad\\wwwroot\\","BasePath":"/","RelativePath":"pages/departamentos#[.{fingerprint}]?.html","AssetKind":"All","AssetMode":"All","AssetRole":"Primary","AssetMergeBehavior":null,"AssetMergeSource":"","RelatedAsset":null,"AssetTraitName":null,"AssetTraitValue":null,"Fingerprint":"fza5rv6uzy","Integrity":"233ShoA62r1vPXWRfiY8CnqpKN7\u002BB7bQRhgKV\u002BPQ0t8=","CopyToOutputDirectory":"Never","CopyToPublishDirectory":"PreserveNewest","OriginalItemSpec":"wwwroot\\pages\\departamentos.html","FileLength":770,"LastWriteTime":"2026-05-06T05:32:06.487648+00:00"},"Iu2BpEsQAnkiwMzCAMxdcp/ze1KIZjwQ6nDE69mpXhI=":{"Identity":"C:\\aaaaaa\\GestionCalidad\\wwwroot\\pages\\informes.html","SourceId":"GestionCalidad","SourceType":"Discovered","ContentRoot":"C:\\aaaaaa\\GestionCalidad\\wwwroot\\","BasePath":"/","RelativePath":"pages/informes#[.{fingerprint}]?.html","AssetKind":"All","AssetMode":"All","AssetRole":"Primary","AssetMergeBehavior":null,"AssetMergeSource":"","RelatedAsset":null,"AssetTraitName":null,"AssetTraitValue":null,"Fingerprint":"bth3oklibk","Integrity":"EcvJQBJ9EmrPBgk\u002Bm5O/K5LBBJWuEiclF4r4PvZXQLg=","CopyToOutputDirectory":"Never","CopyToPublishDirectory":"PreserveNewest","OriginalItemSpec":"wwwroot\\pages\\informes.html","FileLength":989,"LastWriteTime":"2026-05-06T05:42:12.7783057+00:00"},"n4BP7UwxrlnXc5faVpMlimg7CY5VeaBA3fWcqY7Y3pE=":{"Identity":"C:\\aaaaaa\\GestionCalidad\\wwwroot\\js\\informeCalidadDepartamento.js","SourceId":"GestionCalidad","SourceType":"Discovered","ContentRoot":"C:\\aaaaaa\\GestionCalidad\\wwwroot\\","BasePath":"/","RelativePath":"js/informeCalidadDepartamento#[.{fingerprint}]?.js","AssetKind":"All","AssetMode":"All","AssetRole":"Primary","AssetMergeBehavior":null,"AssetMergeSource":"","RelatedAsset":null,"AssetTraitName":null,"AssetTraitValue":null,"Fingerprint":"asr8650ati","Integrity":"VkdXgfMKWtfsfGcxnWkCq29JvEE76IMSIkSn0FIlsW8=","CopyToOutputDirectory":"Never","CopyToPublishDirectory":"PreserveNewest","OriginalItemSpec":"wwwroot\\js\\informeCalidadDepartamento.js","FileLength":2245,"LastWriteTime":"2026-05-06T12:26:45.8113041+00:00"},"h3XMfdqblLF4yYeHjfFIQghFFSxR0IYygRZZEUxnVCI=":{"Identity":"C:\\aaaaaa\\GestionCalidad\\wwwroot\\pages\\reportes.html","SourceId":"GestionCalidad","SourceType":"Discovered","ContentRoot":"C:\\aaaaaa\\GestionCalidad\\wwwroot\\","BasePath":"/","RelativePath":"pages/reportes#[.{fingerprint}]?.html","AssetKind":"All","AssetMode":"All","AssetRole":"Primary","AssetMergeBehavior":null,"AssetMergeSource":"","RelatedAsset":null,"AssetTraitName":null,"AssetTraitValue":null,"Fingerprint":"13ste6p63q","Integrity":"bemUqHSmD8ZL2YtwRPBWCyWByfngBptG\u002BSmx\u002BKbysds=","CopyToOutputDirectory":"Never","CopyToPublishDirectory":"PreserveNewest","OriginalItemSpec":"wwwroot\\pages\\reportes.html","FileLength":1386,"LastWriteTime":"2026-05-06T05:48:26.184078+00:00"},"fHJ9WDOx015/b\u002Bq45CCq4A\u002BDaGkI0wodDKPWBYzssaw=":{"Identity":"C:\\aaaaaa\\GestionCalidad\\wwwroot\\js\\informes.js","SourceId":"GestionCalidad","SourceType":"Discovered","ContentRoot":"C:\\aaaaaa\\GestionCalidad\\wwwroot\\","BasePath":"/","RelativePath":"js/informes#[.{fingerprint}]?.js","AssetKind":"All","AssetMode":"All","AssetRole":"Primary","AssetMergeBehavior":null,"AssetMergeSource":"","RelatedAsset":null,"AssetTraitName":null,"AssetTraitValue":null,"Fingerprint":"v5z8kw71go","Integrity":"/dfcO06pkfOmKaog1i0rz8QEobvfVmjHn/zAbMtJWRs=","CopyToOutputDirectory":"Never","CopyToPublishDirectory":"PreserveNewest","OriginalItemSpec":"wwwroot\\js\\informes.js","FileLength":1726,"LastWriteTime":"2026-05-06T05:43:53.3826404+00:00"},"CYsh96Ktq3NJuuwfp5CaRUCGc8\u002BGb2zfXn6psaM973E=":{"Identity":"C:\\aaaaaa\\GestionCalidad\\wwwroot\\js\\reportes.js","SourceId":"GestionCalidad","SourceType":"Discovered","ContentRoot":"C:\\aaaaaa\\GestionCalidad\\wwwroot\\","BasePath":"/","RelativePath":"js/reportes#[.{fingerprint}]?.js","AssetKind":"All","AssetMode":"All","AssetRole":"Primary","AssetMergeBehavior":null,"AssetMergeSource":"","RelatedAsset":null,"AssetTraitName":null,"AssetTraitValue":null,"Fingerprint":"vhlai5rsjf","Integrity":"U8EOQ\u002BY5sAoCgPupZjoaGtJjF0BMIYGgg1Zw3rXXa3Y=","CopyToOutputDirectory":"Never","CopyToPublishDirectory":"PreserveNewest","OriginalItemSpec":"wwwroot\\js\\reportes.js","FileLength":1625,"LastWriteTime":"2026-05-06T05:49:02.5026422+00:00"},"c8KxDuCX9H5E1bNQLT7sdUXdSo9UHrUBUPbyrDQyRok=":{"Identity":"C:\\aaaaaa\\GestionCalidad\\wwwroot\\wwwroot\\css\\styles.css","SourceId":"GestionCalidad","SourceType":"Discovered","ContentRoot":"C:\\aaaaaa\\GestionCalidad\\wwwroot\\","BasePath":"/","RelativePath":"wwwroot/css/styles#[.{fingerprint}]?.css","AssetKind":"All","AssetMode":"All","AssetRole":"Primary","AssetMergeBehavior":null,"AssetMergeSource":"","RelatedAsset":null,"AssetTraitName":null,"AssetTraitValue":null,"Fingerprint":"kgdubres10","Integrity":"XEkezFFKs06mp4/iCWkI3btGrRwsKgjQRes4mcSVGbc=","CopyToOutputDirectory":"Never","CopyToPublishDirectory":"PreserveNewest","OriginalItemSpec":"wwwroot\\wwwroot\\css\\styles.css","FileLength":1537,"LastWriteTime":"2026-05-06T06:00:25.10666+00:00"},"mshqV7RNKI/zjkrqKfz4rFk6XyGRGZgjfZVjA0j2okQ=":{"Identity":"C:\\aaaaaa\\GestionCalidad\\wwwroot\\wwwroot\\index.html","SourceId":"GestionCalidad","SourceType":"Discovered","ContentRoot":"C:\\aaaaaa\\GestionCalidad\\wwwroot\\","BasePath":"/","RelativePath":"wwwroot/index#[.{fingerprint}]?.html","AssetKind":"All","AssetMode":"All","AssetRole":"Primary","AssetMergeBehavior":null,"AssetMergeSource":"","RelatedAsset":null,"AssetTraitName":null,"AssetTraitValue":null,"Fingerprint":"6f3w81hrez","Integrity":"rqoGCvpDh96VFx9kv0ybQxwpuN8fTIG1iOIq/NJO2oc=","CopyToOutputDirectory":"Never","CopyToPublishDirectory":"PreserveNewest","OriginalItemSpec":"wwwroot\\wwwroot\\index.html","FileLength":1383,"LastWriteTime":"2026-05-06T12:27:19.7080116+00:00"},"JWZpCwETsApNW1hcp9mxdCkB8MzOazRuCu330h6RBn8=":{"Identity":"C:\\aaaaaa\\GestionCalidad\\wwwroot\\wwwroot\\js\\departamentos.js","SourceId":"GestionCalidad","SourceType":"Discovered","ContentRoot":"C:\\aaaaaa\\GestionCalidad\\wwwroot\\","BasePath":"/","RelativePath":"wwwroot/js/departamentos#[.{fingerprint}]?.js","AssetKind":"All","AssetMode":"All","AssetRole":"Primary","AssetMergeBehavior":null,"AssetMergeSource":"","RelatedAsset":null,"AssetTraitName":null,"AssetTraitValue":null,"Fingerprint":"ah2o1dinpu","Integrity":"jvd8TZS1w/5za/B2qO7w5v7CcH4qMO0qi7awpwbCSbo=","CopyToOutputDirectory":"Never","CopyToPublishDirectory":"PreserveNewest","OriginalItemSpec":"wwwroot\\wwwroot\\js\\departamentos.js","FileLength":1168,"LastWriteTime":"2026-05-06T05:37:52.1535938+00:00"},"njyi1Wwg/A2K8CoLhMtFfmQYAvX4gy68sR\u002Br0bAxWzw=":{"Identity":"C:\\aaaaaa\\GestionCalidad\\wwwroot\\wwwroot\\js\\enfermeras.js","SourceId":"GestionCalidad","SourceType":"Discovered","ContentRoot":"C:\\aaaaaa\\GestionCalidad\\wwwroot\\","BasePath":"/","RelativePath":"wwwroot/js/enfermeras#[.{fingerprint}]?.js","AssetKind":"All","AssetMode":"All","AssetRole":"Primary","AssetMergeBehavior":null,"AssetMergeSource":"","RelatedAsset":null,"AssetTraitName":null,"AssetTraitValue":null,"Fingerprint":"x89vtlpnmp","Integrity":"kUEXN9oFp9JIn4lpz401VI19kB0QsGuA9dmsSdacwQI=","CopyToOutputDirectory":"Never","CopyToPublishDirectory":"PreserveNewest","OriginalItemSpec":"wwwroot\\wwwroot\\js\\enfermeras.js","FileLength":723,"LastWriteTime":"2026-05-06T06:59:39.4928941+00:00"},"PTz6\u002B/pNrwuTQR2t23JEg1aMfBGLg2YtSrXGoah8a6g=":{"Identity":"C:\\aaaaaa\\GestionCalidad\\wwwroot\\wwwroot\\js\\informeCalidadDepartamento.js","SourceId":"GestionCalidad","SourceType":"Discovered","ContentRoot":"C:\\aaaaaa\\GestionCalidad\\wwwroot\\","BasePath":"/","RelativePath":"wwwroot/js/informeCalidadDepartamento#[.{fingerprint}]?.js","AssetKind":"All","AssetMode":"All","AssetRole":"Primary","AssetMergeBehavior":null,"AssetMergeSource":"","RelatedAsset":null,"AssetTraitName":null,"AssetTraitValue":null,"Fingerprint":"asr8650ati","Integrity":"VkdXgfMKWtfsfGcxnWkCq29JvEE76IMSIkSn0FIlsW8=","CopyToOutputDirectory":"Never","CopyToPublishDirectory":"PreserveNewest","OriginalItemSpec":"wwwroot\\wwwroot\\js\\informeCalidadDepartamento.js","FileLength":2245,"LastWriteTime":"2026-05-06T12:26:45.8113041+00:00"},"uAvNU5AJO9OwYJ42VkdYyvNo9ST4W/fa\u002B1RPgxztXGQ=":{"Identity":"C:\\aaaaaa\\GestionCalidad\\wwwroot\\wwwroot\\js\\informeQuejaDepartamento.js","SourceId":"GestionCalidad","SourceType":"Discovered","ContentRoot":"C:\\aaaaaa\\GestionCalidad\\wwwroot\\","BasePath":"/","RelativePath":"wwwroot/js/informeQuejaDepartamento#[.{fingerprint}]?.js","AssetKind":"All","AssetMode":"All","AssetRole":"Primary","AssetMergeBehavior":null,"AssetMergeSource":"","RelatedAsset":null,"AssetTraitName":null,"AssetTraitValue":null,"Fingerprint":"n6kt478won","Integrity":"kXQFQBNwoeq7UUxWgXTGUvpud0\u002BimsI99u3RmsZH0FU=","CopyToOutputDirectory":"Never","CopyToPublishDirectory":"PreserveNewest","OriginalItemSpec":"wwwroot\\wwwroot\\js\\informeQuejaDepartamento.js","FileLength":2353,"LastWriteTime":"2026-05-06T12:14:21.612723+00:00"},"Gs4ZpsE5ukXYrbpVg/gMXxxOWwPJPFnxNPQPay2r0Mc=":{"Identity":"C:\\aaaaaa\\GestionCalidad\\wwwroot\\wwwroot\\js\\informes.js","SourceId":"GestionCalidad","SourceType":"Discovered","ContentRoot":"C:\\aaaaaa\\GestionCalidad\\wwwroot\\","BasePath":"/","RelativePath":"wwwroot/js/informes#[.{fingerprint}]?.js","AssetKind":"All","AssetMode":"All","AssetRole":"Primary","AssetMergeBehavior":null,"AssetMergeSource":"","RelatedAsset":null,"AssetTraitName":null,"AssetTraitValue":null,"Fingerprint":"v5z8kw71go","Integrity":"/dfcO06pkfOmKaog1i0rz8QEobvfVmjHn/zAbMtJWRs=","CopyToOutputDirectory":"Never","CopyToPublishDirectory":"PreserveNewest","OriginalItemSpec":"wwwroot\\wwwroot\\js\\informes.js","FileLength":1726,"LastWriteTime":"2026-05-06T05:43:53.3826404+00:00"},"qhJApNgzSk\u002BUxx6M8ksgqCXr0566pJNlv/UVjXBpUus=":{"Identity":"C:\\aaaaaa\\GestionCalidad\\wwwroot\\wwwroot\\js\\quejas.js","SourceId":"GestionCalidad","SourceType":"Discovered","ContentRoot":"C:\\aaaaaa\\GestionCalidad\\wwwroot\\","BasePath":"/","RelativePath":"wwwroot/js/quejas#[.{fingerprint}]?.js","AssetKind":"All","AssetMode":"All","AssetRole":"Primary","AssetMergeBehavior":null,"AssetMergeSource":"","RelatedAsset":null,"AssetTraitName":null,"AssetTraitValue":null,"Fingerprint":"97h2vy57zk","Integrity":"lRpIa/chJLx11kLZDWxBHn9nxrg14vGL5c2IpeqkNu8=","CopyToOutputDirectory":"Never","CopyToPublishDirectory":"PreserveNewest","OriginalItemSpec":"wwwroot\\wwwroot\\js\\quejas.js","FileLength":1544,"LastWriteTime":"2026-05-06T12:21:46.2993478+00:00"},"g6fXc6qMcpNkrpzuXsDXplZsaLRaWs\u002BysVOGIeDD\u002BuY=":{"Identity":"C:\\aaaaaa\\GestionCalidad\\wwwroot\\wwwroot\\js\\reportes.js","SourceId":"GestionCalidad","SourceType":"Discovered","ContentRoot":"C:\\aaaaaa\\GestionCalidad\\wwwroot\\","BasePath":"/","RelativePath":"wwwroot/js/reportes#[.{fingerprint}]?.js","AssetKind":"All","AssetMode":"All","AssetRole":"Primary","AssetMergeBehavior":null,"AssetMergeSource":"","RelatedAsset":null,"AssetTraitName":null,"AssetTraitValue":null,"Fingerprint":"vhlai5rsjf","Integrity":"U8EOQ\u002BY5sAoCgPupZjoaGtJjF0BMIYGgg1Zw3rXXa3Y=","CopyToOutputDirectory":"Never","CopyToPublishDirectory":"PreserveNewest","OriginalItemSpec":"wwwroot\\wwwroot\\js\\reportes.js","FileLength":1625,"LastWriteTime":"2026-05-06T05:49:02.5026422+00:00"},"PAOtwT\u002BVmzWbeleg2IzES2lFUCvaWb6AeMtOZeXavjU=":{"Identity":"C:\\aaaaaa\\GestionCalidad\\wwwroot\\wwwroot\\pages\\departamentos.html","SourceId":"GestionCalidad","SourceType":"Discovered","ContentRoot":"C:\\aaaaaa\\GestionCalidad\\wwwroot\\","BasePath":"/","RelativePath":"wwwroot/pages/departamentos#[.{fingerprint}]?.html","AssetKind":"All","AssetMode":"All","AssetRole":"Primary","AssetMergeBehavior":null,"AssetMergeSource":"","RelatedAsset":null,"AssetTraitName":null,"AssetTraitValue":null,"Fingerprint":"fza5rv6uzy","Integrity":"233ShoA62r1vPXWRfiY8CnqpKN7\u002BB7bQRhgKV\u002BPQ0t8=","CopyToOutputDirectory":"Never","CopyToPublishDirectory":"PreserveNewest","OriginalItemSpec":"wwwroot\\wwwroot\\pages\\departamentos.html","FileLength":770,"LastWriteTime":"2026-05-06T05:32:06.487648+00:00"},"qIcVGL8QUA1Yic9BPPKYaqQwaJ89oXZo8WAOw8E6AGs=":{"Identity":"C:\\aaaaaa\\GestionCalidad\\wwwroot\\wwwroot\\pages\\enfermeras.html","SourceId":"GestionCalidad","SourceType":"Discovered","ContentRoot":"C:\\aaaaaa\\GestionCalidad\\wwwroot\\","BasePath":"/","RelativePath":"wwwroot/pages/enfermeras#[.{fingerprint}]?.html","AssetKind":"All","AssetMode":"All","AssetRole":"Primary","AssetMergeBehavior":null,"AssetMergeSource":"","RelatedAsset":null,"AssetTraitName":null,"AssetTraitValue":null,"Fingerprint":"qcnharil75","Integrity":"hnm\u002BC\u002B0oJK/SCtMnVlOM/Mi3O4t1\u002BEe/WVux3lQKYBg=","CopyToOutputDirectory":"Never","CopyToPublishDirectory":"PreserveNewest","OriginalItemSpec":"wwwroot\\wwwroot\\pages\\enfermeras.html","FileLength":754,"LastWriteTime":"2026-05-06T07:02:36.455953+00:00"},"N3r\u002BdL5XSPA8AvKBQvD8vVWRsuBRt669r6\u002Ba/svrHys=":{"Identity":"C:\\aaaaaa\\GestionCalidad\\wwwroot\\wwwroot\\pages\\informeCalidadDepartamento.html","SourceId":"GestionCalidad","SourceType":"Discovered","ContentRoot":"C:\\aaaaaa\\GestionCalidad\\wwwroot\\","BasePath":"/","RelativePath":"wwwroot/pages/informeCalidadDepartamento#[.{fingerprint}]?.html","AssetKind":"All","AssetMode":"All","AssetRole":"Primary","AssetMergeBehavior":null,"AssetMergeSource":"","RelatedAsset":null,"AssetTraitName":null,"AssetTraitValue":null,"Fingerprint":"5cuh6zvdki","Integrity":"K\u002BrcqbhtSVjlSOgF7nzklVFGKsAc5W\u002BUwo04aMEql3U=","CopyToOutputDirectory":"Never","CopyToPublishDirectory":"PreserveNewest","OriginalItemSpec":"wwwroot\\wwwroot\\pages\\informeCalidadDepartamento.html","FileLength":1057,"LastWriteTime":"2026-05-06T12:26:32.1603854+00:00"},"NYtcuqvjYk3mg9w5e7k8ELz8njkQokbBAJjDWUJuI40=":{"Identity":"C:\\aaaaaa\\GestionCalidad\\wwwroot\\wwwroot\\pages\\informeQuejaDepartamento.html","SourceId":"GestionCalidad","SourceType":"Discovered","ContentRoot":"C:\\aaaaaa\\GestionCalidad\\wwwroot\\","BasePath":"/","RelativePath":"wwwroot/pages/informeQuejaDepartamento#[.{fingerprint}]?.html","AssetKind":"All","AssetMode":"All","AssetRole":"Primary","AssetMergeBehavior":null,"AssetMergeSource":"","RelatedAsset":null,"AssetTraitName":null,"AssetTraitValue":null,"Fingerprint":"q5z7zqx05o","Integrity":"Qpc\u002BYlaGEJOC\u002BxPzIUID09RY2ImDP2bv4vsuzymHoZU=","CopyToOutputDirectory":"Never","CopyToPublishDirectory":"PreserveNewest","OriginalItemSpec":"wwwroot\\wwwroot\\pages\\informeQuejaDepartamento.html","FileLength":1075,"LastWriteTime":"2026-05-06T12:14:30.4963401+00:00"},"4ZMWFWm0ynvuOwtLVe7MGK7ySanpo2xd7HDBECRpTkQ=":{"Identity":"C:\\aaaaaa\\GestionCalidad\\wwwroot\\wwwroot\\pages\\informes.html","SourceId":"GestionCalidad","SourceType":"Discovered","ContentRoot":"C:\\aaaaaa\\GestionCalidad\\wwwroot\\","BasePath":"/","RelativePath":"wwwroot/pages/informes#[.{fingerprint}]?.html","AssetKind":"All","AssetMode":"All","AssetRole":"Primary","AssetMergeBehavior":null,"AssetMergeSource":"","RelatedAsset":null,"AssetTraitName":null,"AssetTraitValue":null,"Fingerprint":"bth3oklibk","Integrity":"EcvJQBJ9EmrPBgk\u002Bm5O/K5LBBJWuEiclF4r4PvZXQLg=","CopyToOutputDirectory":"Never","CopyToPublishDirectory":"PreserveNewest","OriginalItemSpec":"wwwroot\\wwwroot\\pages\\informes.html","FileLength":989,"LastWriteTime":"2026-05-06T05:42:12.7783057+00:00"},"zLTG5jugf0NHqV0CQe6i1b\u002BRH7cUXS5w63vUlt9IS30=":{"Identity":"C:\\aaaaaa\\GestionCalidad\\wwwroot\\wwwroot\\pages\\quejas.html","SourceId":"GestionCalidad","SourceType":"Discovered","ContentRoot":"C:\\aaaaaa\\GestionCalidad\\wwwroot\\","BasePath":"/","RelativePath":"wwwroot/pages/quejas#[.{fingerprint}]?.html","AssetKind":"All","AssetMode":"All","AssetRole":"Primary","AssetMergeBehavior":null,"AssetMergeSource":"","RelatedAsset":null,"AssetTraitName":null,"AssetTraitValue":null,"Fingerprint":"bpjpyz3o24","Integrity":"AdLsOBGN083L6sudJH/2Hr5vSOHKH94MY3ZHAr5o6co=","CopyToOutputDirectory":"Never","CopyToPublishDirectory":"PreserveNewest","OriginalItemSpec":"wwwroot\\wwwroot\\pages\\quejas.html","FileLength":855,"LastWriteTime":"2026-05-06T12:02:20.4367335+00:00"},"kfVexCzatEDLx3qUadJ8AGldScgUqw55gIF\u002BUYYP4wk=":{"Identity":"C:\\aaaaaa\\GestionCalidad\\wwwroot\\wwwroot\\pages\\reportes.html","SourceId":"GestionCalidad","SourceType":"Discovered","ContentRoot":"C:\\aaaaaa\\GestionCalidad\\wwwroot\\","BasePath":"/","RelativePath":"wwwroot/pages/reportes#[.{fingerprint}]?.html","AssetKind":"All","AssetMode":"All","AssetRole":"Primary","AssetMergeBehavior":null,"AssetMergeSource":"","RelatedAsset":null,"AssetTraitName":null,"AssetTraitValue":null,"Fingerprint":"13ste6p63q","Integrity":"bemUqHSmD8ZL2YtwRPBWCyWByfngBptG\u002BSmx\u002BKbysds=","CopyToOutputDirectory":"Never","CopyToPublishDirectory":"PreserveNewest","OriginalItemSpec":"wwwroot\\wwwroot\\pages\\reportes.html","FileLength":1386,"LastWriteTime":"2026-05-06T05:48:26.184078+00:00"},"LyvSsSkVIbZ3292LaPuwZVWcmvJcZOa9azBZeQYG7Iw=":{"Identity":"C:\\aaaaaa\\GestionCalidad\\wwwroot\\pages\\enfermeras.html","SourceId":"GestionCalidad","SourceType":"Discovered","ContentRoot":"C:\\aaaaaa\\GestionCalidad\\wwwroot\\","BasePath":"/","RelativePath":"pages/enfermeras#[.{fingerprint}]?.html","AssetKind":"All","AssetMode":"All","AssetRole":"Primary","AssetMergeBehavior":null,"AssetMergeSource":"","RelatedAsset":null,"AssetTraitName":null,"AssetTraitValue":null,"Fingerprint":"qcnharil75","Integrity":"hnm\u002BC\u002B0oJK/SCtMnVlOM/Mi3O4t1\u002BEe/WVux3lQKYBg=","CopyToOutputDirectory":"Never","CopyToPublishDirectory":"PreserveNewest","OriginalItemSpec":"wwwroot\\pages\\enfermeras.html","FileLength":754,"LastWriteTime":"2026-05-06T07:02:36.455953+00:00"},"FrV8jdkJqSDvw3ore3jW3uD/KYtsnqS9NOoKv66meCQ=":{"Identity":"C:\\aaaaaa\\GestionCalidad\\wwwroot\\pages\\informeCalidadDepartamento.html","SourceId":"GestionCalidad","SourceType":"Discovered","ContentRoot":"C:\\aaaaaa\\GestionCalidad\\wwwroot\\","BasePath":"/","RelativePath":"pages/informeCalidadDepartamento#[.{fingerprint}]?.html","AssetKind":"All","AssetMode":"All","AssetRole":"Primary","AssetMergeBehavior":null,"AssetMergeSource":"","RelatedAsset":null,"AssetTraitName":null,"AssetTraitValue":null,"Fingerprint":"5cuh6zvdki","Integrity":"K\u002BrcqbhtSVjlSOgF7nzklVFGKsAc5W\u002BUwo04aMEql3U=","CopyToOutputDirectory":"Never","CopyToPublishDirectory":"PreserveNewest","OriginalItemSpec":"wwwroot\\pages\\informeCalidadDepartamento.html","FileLength":1057,"LastWriteTime":"2026-05-06T12:26:32.1603854+00:00"},"GJ7cftWF3rDzSYtsNtVTkHa9q3imFJ2niPTYisgU3S8=":{"Identity":"C:\\aaaaaa\\GestionCalidad\\wwwroot\\pages\\informeQuejaDepartamento.html","SourceId":"GestionCalidad","SourceType":"Discovered","ContentRoot":"C:\\aaaaaa\\GestionCalidad\\wwwroot\\","BasePath":"/","RelativePath":"pages/informeQuejaDepartamento#[.{fingerprint}]?.html","AssetKind":"All","AssetMode":"All","AssetRole":"Primary","AssetMergeBehavior":null,"AssetMergeSource":"","RelatedAsset":null,"AssetTraitName":null,"AssetTraitValue":null,"Fingerprint":"q5z7zqx05o","Integrity":"Qpc\u002BYlaGEJOC\u002BxPzIUID09RY2ImDP2bv4vsuzymHoZU=","CopyToOutputDirectory":"Never","CopyToPublishDirectory":"PreserveNewest","OriginalItemSpec":"wwwroot\\pages\\informeQuejaDepartamento.html","FileLength":1075,"LastWriteTime":"2026-05-06T12:14:30.4963401+00:00"},"SJ5ZDBZgCm8cuy1m/oWwVgLTQBZjWK5uIKi8yontl84=":{"Identity":"C:\\aaaaaa\\GestionCalidad\\wwwroot\\pages\\quejas.html","SourceId":"GestionCalidad","SourceType":"Discovered","ContentRoot":"C:\\aaaaaa\\GestionCalidad\\wwwroot\\","BasePath":"/","RelativePath":"pages/quejas#[.{fingerprint}]?.html","AssetKind":"All","AssetMode":"All","AssetRole":"Primary","AssetMergeBehavior":null,"AssetMergeSource":"","RelatedAsset":null,"AssetTraitName":null,"AssetTraitValue":null,"Fingerprint":"bpjpyz3o24","Integrity":"AdLsOBGN083L6sudJH/2Hr5vSOHKH94MY3ZHAr5o6co=","CopyToOutputDirectory":"Never","CopyToPublishDirectory":"PreserveNewest","OriginalItemSpec":"wwwroot\\pages\\quejas.html","FileLength":855,"LastWriteTime":"2026-05-06T12:02:20.4367335+00:00"}},"CachedCopyCandidates":{}}